setup.cfg
setup.py
donecal/__init__.py
donecal/donecal.py
donecal.egg-info/PKG-INFO
donecal.egg-info/SOURCES.txt
donecal.egg-info/dependency_links.txt
donecal.egg-info/entry_points.txt
donecal.egg-info/not-zip-safe
donecal.egg-info/requires.txt
donecal.egg-info/top_level.txt