Metadata-Version: 1.0
Name: donecal
Version: 0.1dev
Summary: Python interface for the donecal.com restful HTTP API
Home-page: http://donecal.com/help/api#python
Author: Peter Bengtsson
Author-email: mail@peterbe.com
License: BSD
Keywords: donecal rest api donecal.com
Platform: UNKNOWN
